{
  "cosmos-kit": {
    "total": 23277,
    "packages": {
      "cosmos-kit": 667,
      "@cosmos-kit/core": 10669,
      "@cosmos-kit/react": 1928,
      "@cosmos-kit/react-lite": 3243,
      "@cosmos-kit/walletconnect": 6770
    }
  },
  "cosmos-kit-wallets": {
    "total": 102042,
    "packages": {
      "@cosmos-kit/frontier-extension": 931,
      "@cosmos-kit/ledger": 1117,
      "@cosmos-kit/cosmos-extension-metamask": 1429,
      "@cosmos-kit/fin": 1229,
      "@cosmos-kit/coin98-extension": 1023,
      "@cosmos-kit/okxwallet-extension": 3179,
      "@cosmos-kit/trust-mobile": 1050,
      "@cosmos-kit/shell": 997,
      "@cosmos-kit/leap-capsule-social-login": 78,
      "@cosmos-kit/cosmostation-extension": 4530,
      "@cosmos-kit/vectis": 1112,
      "@cosmos-kit/fin-extension": 1339,
      "@cosmos-kit/ninji": 448,
      "@cosmos-kit/station-extension": 3678,
      "@cosmos-kit/coin98": 1063,
      "@cosmos-kit/leap-extension": 6489,
      "@cosmos-kit/exodus": 918,
      "@cosmos-kit/trust-extension": 1008,
      "@cosmos-kit/leap": 6046,
      "@cosmos-kit/xdefi": 3218,
      "@cosmos-kit/web3auth": 373,
      "@cosmos-kit/initia-extension": 98,
      "@cosmos-kit/cosmostation": 4280,
      "@cosmos-kit/shell-extension": 1001,
      "@cosmos-kit/cosmostation-mobile": 4264,
      "@cosmos-kit/vectis-extension": 1109,
      "@cosmos-kit/station": 3720,
      "@cosmos-kit/exodus-extension": 922,
      "@cosmos-kit/leap-mobile": 5992,
      "@cosmos-kit/initia": 96,
      "@cosmos-kit/frontier": 939,
      "@cosmos-kit/trust": 1073,
      "@cosmos-kit/compass": 1123,
      "@cosmos-kit/keplr-mobile": 6479,
      "@cosmos-kit/keplr-extension": 6838,
      "@cosmos-kit/ninji-extension": 464,
      "@cosmos-kit/compass-extension": 1414,
      "@cosmos-kit/xdefi-extension": 3625,
      "@cosmos-kit/okxwallet": 2540,
      "@cosmos-kit/omni": 1134,
      "@cosmos-kit/keplr": 6415,
      "@cosmos-kit/omni-mobile": 1161,
      "@cosmos-kit/leap-metamask-cosmos-snap": 6100
    }
  },
  "cosmwasm": {
    "total": 30163,
    "packages": {
      "@cosmwasm/ts-codegen": 30163
    }
  },
  "interchain-ui": {
    "total": 2566,
    "packages": {
      "@interchain-ui/react": 2566
    }
  },
  "telescope": {
    "total": 58288,
    "packages": {
      "@cosmology/telescope": 4666,
      "@cosmology/lcd": 4919,
      "@cosmology/ast": 4529,
      "@osmonauts/telescope": 7754,
      "@osmonauts/lcd": 28631,
      "@osmonauts/ast": 7789
    }
  },
  "dydx": {
    "total": 3473,
    "packages": {
      "@dydxprotocol/v4-client-js": 3473
    }
  },
  "stargaze": {
    "total": 406,
    "packages": {
      "stargazejs": 143,
      "@stargaze-zone/chain": 52,
      "@stargaze-zone/contracts": 45,
      "stargaze-query": 166
    }
  },
  "stride": {
    "total": 596,
    "packages": {
      "stridejs": 596
    }
  },
  "quicksilver": {
    "total": 135,
    "packages": {
      "quicksilverjs": 135
    }
  },
  "juno": {
    "total": 299,
    "packages": {
      "juno-network": 292,
      "@juno-network/assets": 7
    }
  },
  "osmosis": {
    "total": 7414,
    "packages": {
      "@osmonauts/math": 448,
      "osmojs": 6966
    }
  },
  "chain-registry": {
    "total": 84078,
    "packages": {
      "@chain-registry/client": 5285,
      "@chain-registry/types": 30080,
      "@chain-registry/keplr": 8202,
      "@chain-registry/cosmostation": 9218,
      "@chain-registry/osmosis": 1796,
      "@chain-registry/juno": 757,
      "@chain-registry/assets": 1012,
      "@chain-registry/utils": 8815,
      "chain-registry": 18913
    }
  },
  "cosmology": {
    "total": 1769,
    "packages": {
      "@cosmology/cli": 27,
      "@cosmology/core": 511,
      "cosmology": 22,
      "create-cosmos-app": 405,
      "interchain": 94,
      "interchain-query": 305
    }
  },
  "launchql": {
    "total": 135482,
    "packages": {
      "libpg-query": 38978,
      "pgsql-parser": 32286,
      "pgsql-enums": 32005,
      "pgsql-deparser": 32213
    }
  },
  "protobufs": {
    "total": 109169,
    "packages": {
      "@protobufs/cosmos": 16321,
      "@protobufs/google": 16543,
      "@protobufs/gogoproto": 16543,
      "@protobufs/cosmwasm": 8839,
      "@protobufs/tendermint": 16290,
      "@protobufs/ibc": 8840,
      "@protobufs/cosmos_proto": 16358,
      "@protobufs/osmosis": 265,
      "@protobufs/secret": 1,
      "@protobufs/juno": 12,
      "@protobufs/akash": 4,
      "@protobufs/regen": 4,
      "@protobufs/pylons": 2,
      "@protobufs/stargaze": 13,
      "@protobufs/bcna": 4,
      "@protobufs/comdex": 4,
      "@protobufs/evmos": 2,
      "@protobufs/axelar": 2,
      "@protobufs/amino": 9122
    }
  }
}