{
  "cosmos-kit": {
    "total": 95718,
    "packages": {
      "cosmos-kit": 3723,
      "@cosmos-kit/core": 37918,
      "@cosmos-kit/react": 9868,
      "@cosmos-kit/react-lite": 12105,
      "@cosmos-kit/walletconnect": 32104
    }
  },
  "cosmos-kit-wallets": {
    "total": 614543,
    "packages": {
      "@cosmos-kit/frontier-extension": 4532,
      "@cosmos-kit/ledger": 4500,
      "@cosmos-kit/cosmos-extension-metamask": 1353,
      "@cosmos-kit/fin": 4294,
      "@cosmos-kit/coin98-extension": 4331,
      "@cosmos-kit/okxwallet-extension": 26419,
      "@cosmos-kit/trust-mobile": 25427,
      "@cosmos-kit/shell": 4189,
      "@cosmos-kit/leap-capsule-social-login": 199,
      "@cosmos-kit/cosmostation-extension": 30141,
      "@cosmos-kit/vectis": 5828,
      "@cosmos-kit/fin-extension": 4434,
      "@cosmos-kit/ninji": 548,
      "@cosmos-kit/station-extension": 27298,
      "@cosmos-kit/coin98": 4324,
      "@cosmos-kit/leap-extension": 32097,
      "@cosmos-kit/exodus": 4203,
      "@cosmos-kit/trust-extension": 25241,
      "@cosmos-kit/leap": 29666,
      "@cosmos-kit/xdefi": 25624,
      "@cosmos-kit/web3auth": 1040,
      "@cosmos-kit/initia-extension": 315,
      "@cosmos-kit/cosmostation": 27773,
      "@cosmos-kit/shell-extension": 4202,
      "@cosmos-kit/cosmostation-mobile": 27583,
      "@cosmos-kit/vectis-extension": 5744,
      "@cosmos-kit/station": 27258,
      "@cosmos-kit/exodus-extension": 4216,
      "@cosmos-kit/leap-mobile": 29628,
      "@cosmos-kit/initia": 312,
      "@cosmos-kit/frontier": 4535,
      "@cosmos-kit/trust": 25380,
      "@cosmos-kit/compass": 4647,
      "@cosmos-kit/keplr-mobile": 30890,
      "@cosmos-kit/keplr-extension": 32996,
      "@cosmos-kit/ninji-extension": 562,
      "@cosmos-kit/compass-extension": 4807,
      "@cosmos-kit/xdefi-extension": 26555,
      "@cosmos-kit/okxwallet": 22831,
      "@cosmos-kit/omni": 4692,
      "@cosmos-kit/keplr": 30621,
      "@cosmos-kit/omni-mobile": 4851,
      "@cosmos-kit/leap-metamask-cosmos-snap": 28457
    }
  },
  "cosmwasm": {
    "total": 146274,
    "packages": {
      "@cosmwasm/ts-codegen": 67392,
      "@cosmwasm/ts-codegen-types": 11635,
      "@cosmwasm/ts-codegen-ast": 11639,
      "wasm-ast-types": 55120,
      "cosmwasm-typescript-gen": 488
    }
  },
  "interchain-ui": {
    "total": 10581,
    "packages": {
      "@interchain-ui/react": 10247,
      "@interchain-ui/vue": 334
    }
  },
  "telescope": {
    "total": 309261,
    "packages": {
      "@cosmology/telescope": 28636,
      "@cosmology/lcd": 18771,
      "@cosmology/ast": 28194,
      "@cosmology/types": 28048,
      "@cosmology/utils": 28134,
      "@cosmology/proto-parser": 28071,
      "@osmonauts/telescope": 16494,
      "@osmonauts/lcd": 69543,
      "@osmonauts/ast": 16216,
      "@osmonauts/utils": 15440,
      "@osmonauts/types": 15795,
      "@osmonauts/proto-parser": 15919
    }
  },
  "dydx": {
    "total": 9903,
    "packages": {
      "@dydxprotocol/v4-client-js": 9903
    }
  },
  "stargaze": {
    "total": 675,
    "packages": {
      "stargazejs": 500,
      "@stargaze-zone/chain": 48,
      "@stargaze-zone/contracts": 52,
      "stargaze-query": 75
    }
  },
  "stride": {
    "total": 1870,
    "packages": {
      "stridejs": 1870
    }
  },
  "quicksilver": {
    "total": 53,
    "packages": {
      "quicksilverjs": 53
    }
  },
  "juno": {
    "total": 1125,
    "packages": {
      "juno-network": 998,
      "@juno-network/assets": 127
    }
  },
  "osmosis": {
    "total": 21944,
    "packages": {
      "@osmonauts/math": 1989,
      "osmojs": 18451,
      "osmo-query": 1504
    }
  },
  "chain-registry": {
    "total": 412261,
    "packages": {
      "@chain-registry/client": 41076,
      "@chain-registry/types": 132528,
      "@chain-registry/keplr": 71324,
      "@chain-registry/cosmostation": 58291,
      "@chain-registry/osmosis": 6535,
      "@chain-registry/juno": 3079,
      "@chain-registry/assets": 3741,
      "@chain-registry/utils": 43154,
      "chain-registry": 52533
    }
  },
  "cosmology": {
    "total": 4708,
    "packages": {
      "cosmjs-utils": 820,
      "@cosmology/cli": 618,
      "@cosmology/core": 1008,
      "cosmology": 245,
      "interchain": 732,
      "interchain-query": 726,
      "create-cosmos-app": 189,
      "create-cosmwasm-app": 57,
      "@cosmology-ui/react": 313
    }
  },
  "starship": {
    "total": 1034,
    "packages": {
      "starshipjs": 558,
      "@starship-ci/cli": 218,
      "@starship-ci/client": 258
    }
  },
  "launchql": {
    "total": null,
    "packages": {
      "@launchql/db-templates": 525,
      "@launchql/db-transform": 203,
      "@launchql/ext-achievements": 214,
      "@launchql/ext-jobs-queue": 179,
      "@launchql/ext-jwt-claims": 175,
      "@launchql/ext-types": 214,
      "@launchql/faker": 209,
      "@launchql/inflection": 194,
      "@launchql/totp": 190,
      "@pgql/parse": 71,
      "@pgsql/enums": 28,
      "@pgsql/parser": 13,
      "@pgsql/types": 67158,
      "@pgsql/utils": 48,
      "@pyramation/postgraphile-plugin-fulltext-filter": 2088,
      "graphile-column-privileges-mutations": 166,
      "libpg-query": 184192,
      "pg-proto-parser": 186,
      "pg-query-native-latest": 17,
      "pg-utils": 124,
      "pgsql-deparser": 127171,
      "pgsql-enums": 127067,
      "pgsql-parser": 127578
    }
  },
  "protobufs": {
    "total": 210243,
    "packages": {
      "@protobufs/cosmos": 24988,
      "@protobufs/google": 25521,
      "@protobufs/gogoproto": 25515,
      "@protobufs/cosmwasm": 10152,
      "@protobufs/tendermint": 24522,
      "@protobufs/ibc": 10159,
      "@protobufs/cosmos_proto": 24510,
      "@protobufs/osmosis": 362,
      "@protobufs/secret": 31,
      "@protobufs/juno": 45,
      "@protobufs/akash": 45,
      "@protobufs/regen": 46,
      "@protobufs/pylons": 29,
      "@protobufs/stargaze": 36,
      "@protobufs/bcna": 40,
      "@protobufs/comdex": 27,
      "@protobufs/evmos": 21,
      "@protobufs/axelar": 15,
      "@protobufs/amino": 10398,
      "@cosmology/protobufjs": 37793,
      "@pyramation/protobufjs": 15988
    }
  },
  "utils": {
    "total": null,
    "packages": {
      "ast-stringify": 56095,
      "nested-obj": 11634,
      "schema-typescript": 1444,
      "etag-hash": 1600,
      "uuid-hash": 1025,
      "inquirerer": 57660,
      "publish-scripts": 442,
      "skitch-template": 289
    }
  }
}