{
  "hyperwebjs": {
    "total": 104,
    "packages": {
      "create-hyperweb-app": 26,
      "@hyperweb/cli": 8,
      "hyperwebjs": 42,
      "hyperweb-kit": 6,
      "@hyperweb/build": 14,
      "@hyperweb/ts-json-schema": 8
    }
  },
  "interchain-js": {
    "total": 24304,
    "packages": {
      "interchainjs": 3689,
      "injectivejs": 564,
      "@interchainjs/utils": 3062,
      "@interchainjs/types": 3122,
      "@interchainjs/auth": 3087,
      "@interchainjs/cosmos": 3195,
      "@interchainjs/cosmos-msgs": 15,
      "@interchainjs/cosmos-query": 16,
      "@interchainjs/ethereum": 1078,
      "@interchainjs/injective": 1183,
      "@interchainjs/cosmos-types": 3996,
      "@interchainjs/ethermint": 28,
      "injective-query": 11,
      "injective-react": 440,
      "injective-vue": 384,
      "interchain-react": 434
    }
  },
  "cosmos-kit": {
    "total": 134051,
    "packages": {
      "interchain-kit": 1458,
      "@interchain-kit/core": 3604,
      "@interchain-kit/react": 1580,
      "@interchain-kit/vue": 805,
      "cosmos-kit": 3412,
      "@cosmos-kit/core": 64105,
      "@cosmos-kit/react": 6749,
      "@cosmos-kit/react-lite": 8023,
      "@cosmos-kit/walletconnect": 44315
    }
  },
  "create-cosmos-app": {
    "total": 337,
    "packages": {
      "create-cosmos-app": 290,
      "create-interchain-app": 47
    }
  },
  "interchain-kit": {
    "total": 7447,
    "packages": {
      "interchain-kit": 1458,
      "@interchain-kit/core": 3604,
      "@interchain-kit/react": 1580,
      "@interchain-kit/vue": 805
    }
  },
  "interchain-kit-wallets": {
    "total": 22605,
    "packages": {
      "@interchain-kit/okx-extension": 1417,
      "@interchain-kit/mock-wallet": 972,
      "@interchain-kit/leap-extension": 1436,
      "@interchain-kit/ledger": 1489,
      "@interchain-kit/coin98-extension": 1497,
      "@interchain-kit/leap-mobile": 1471,
      "@interchain-kit/keplr-mobile": 1474,
      "@interchain-kit/keplr-extension": 1537,
      "@interchain-kit/frontier-extension": 1440,
      "@interchain-kit/station-extension": 1419,
      "@interchain-kit/cosmostation-extension": 1413,
      "@interchain-kit/galaxy-station-extension": 1420,
      "@interchain-kit/vue": 805,
      "@interchain-kit/cosmos-extension-metamask": 1373,
      "@interchain-kit/trust-extension": 1332,
      "@interchain-kit/leap-cosmos-extension-metamask": 1367,
      "@interchain-kit/xdefi-extension": 743
    }
  },
  "cosmos-kit-wallets": {
    "total": 836515,
    "packages": {
      "@interchain-kit/okx-extension": 1417,
      "@interchain-kit/mock-wallet": 972,
      "@interchain-kit/leap-extension": 1436,
      "@interchain-kit/ledger": 1489,
      "@interchain-kit/coin98-extension": 1497,
      "@interchain-kit/leap-mobile": 1471,
      "@interchain-kit/keplr-mobile": 1474,
      "@interchain-kit/keplr-extension": 1537,
      "@interchain-kit/frontier-extension": 1440,
      "@interchain-kit/station-extension": 1419,
      "@interchain-kit/cosmostation-extension": 1413,
      "@interchain-kit/galaxy-station-extension": 1420,
      "@interchain-kit/vue": 805,
      "@interchain-kit/cosmos-extension-metamask": 1373,
      "@interchain-kit/trust-extension": 1332,
      "@interchain-kit/leap-cosmos-extension-metamask": 1367,
      "@interchain-kit/xdefi-extension": 743,
      "@cosmos-kit/frontier-extension": 2521,
      "@cosmos-kit/ledger": 3963,
      "@cosmos-kit/cosmos-extension-metamask": 3000,
      "@cosmos-kit/fin": 3681,
      "@cosmos-kit/coin98-extension": 3739,
      "@cosmos-kit/okxwallet-extension": 37494,
      "@cosmos-kit/trust-mobile": 37669,
      "@cosmos-kit/shell": 3485,
      "@cosmos-kit/leap-capsule-social-login": 342,
      "@cosmos-kit/cosmostation-extension": 40076,
      "@cosmos-kit/vectis": 2451,
      "@cosmos-kit/fin-extension": 3708,
      "@cosmos-kit/ninji": 631,
      "@cosmos-kit/station-extension": 36716,
      "@cosmos-kit/coin98": 3719,
      "@cosmos-kit/leap-extension": 43093,
      "@cosmos-kit/exodus": 3631,
      "@cosmos-kit/trust-extension": 37382,
      "@cosmos-kit/leap": 43172,
      "@cosmos-kit/xdefi": 36295,
      "@cosmos-kit/web3auth": 1512,
      "@cosmos-kit/initia-extension": 313,
      "@cosmos-kit/cosmostation": 39552,
      "@cosmos-kit/shell-extension": 3590,
      "@cosmos-kit/cosmostation-mobile": 39512,
      "@cosmos-kit/vectis-extension": 2461,
      "@cosmos-kit/station": 36506,
      "@cosmos-kit/exodus-extension": 3650,
      "@cosmos-kit/leap-mobile": 42504,
      "@cosmos-kit/initia": 277,
      "@cosmos-kit/frontier": 2499,
      "@cosmos-kit/trust": 37358,
      "@cosmos-kit/compass": 3747,
      "@cosmos-kit/keplr-mobile": 42680,
      "@cosmos-kit/keplr-extension": 43115,
      "@cosmos-kit/ninji-extension": 650,
      "@cosmos-kit/compass-extension": 3838,
      "@cosmos-kit/xdefi-extension": 36514,
      "@cosmos-kit/okxwallet": 34540,
      "@cosmos-kit/omni": 3619,
      "@cosmos-kit/keplr": 42584,
      "@cosmos-kit/omni-mobile": 3775,
      "@cosmos-kit/leap-metamask-cosmos-snap": 42346
    }
  },
  "cosmwasm": {
    "total": 110609,
    "packages": {
      "@cosmwasm/ts-codegen": 54595,
      "@cosmwasm/ts-codegen-types": 1150,
      "@cosmwasm/ts-codegen-ast": 1358,
      "wasm-ast-types": 53331,
      "cosmwasm-typescript-gen": 175
    }
  },
  "interchain-ui": {
    "total": 7419,
    "packages": {
      "@interchain-ui/react": 7110,
      "@interchain-ui/vue": 309
    }
  },
  "telescope": {
    "total": 472292,
    "packages": {
      "@cosmology/telescope": 40116,
      "@cosmology/lcd": 75087,
      "@cosmology/ast": 49336,
      "@cosmology/types": 82325,
      "@cosmology/utils": 82430,
      "@cosmology/proto-parser": 82282,
      "@osmonauts/telescope": 4186,
      "@osmonauts/lcd": 41583,
      "@osmonauts/ast": 3876,
      "@osmonauts/utils": 3644,
      "@osmonauts/types": 3730,
      "@osmonauts/proto-parser": 3697
    }
  },
  "dydx": {
    "total": 18202,
    "packages": {
      "@dydxprotocol/v4-client-js": 18202
    }
  },
  "stargaze": {
    "total": 363,
    "packages": {
      "stargazejs": 189,
      "@stargaze-zone/chain": 49,
      "@stargaze-zone/contracts": 73,
      "stargaze-query": 52
    }
  },
  "stride": {
    "total": 361,
    "packages": {
      "stridejs": 361
    }
  },
  "quicksilver": {
    "total": 95,
    "packages": {
      "quicksilverjs": 95
    }
  },
  "juno": {
    "total": 837,
    "packages": {
      "juno-network": 763,
      "@juno-network/assets": 74
    }
  },
  "osmosis": {
    "total": 14881,
    "packages": {
      "@osmonauts/math": 1328,
      "osmojs": 12382,
      "osmo-query": 1171
    }
  },
  "chain-registry": {
    "total": 692500,
    "packages": {
      "@chain-registry/client": 74365,
      "@chain-registry/types": 232860,
      "@chain-registry/keplr": 107390,
      "@chain-registry/cosmostation": 81244,
      "@chain-registry/osmosis": 3198,
      "@chain-registry/juno": 3363,
      "@chain-registry/assets": 4475,
      "@chain-registry/utils": 99662,
      "chain-registry": 85943
    }
  },
  "cosmology": {
    "total": 21891,
    "packages": {
      "cosmjs-utils": 741,
      "@cosmology/cli": 240,
      "@cosmology/core": 646,
      "cosmology": 355,
      "interchain": 19158,
      "interchain-query": 340,
      "create-cosmos-app": 290,
      "create-cosmwasm-app": 50,
      "@cosmology-ui/react": 71
    }
  },
  "starship": {
    "total": 1559,
    "packages": {
      "starshipjs": 838,
      "@starship-ci/cli": 336,
      "@starship-ci/client": 385
    }
  },
  "launchql": {
    "total": null,
    "packages": {
      "@launchql/db-templates": 262,
      "@launchql/db-transform": 76,
      "@launchql/ext-achievements": 105,
      "@launchql/ext-jobs-queue": 91,
      "@launchql/ext-jwt-claims": 131,
      "@launchql/ext-types": 114,
      "@launchql/faker": 104,
      "@launchql/inflection": 105,
      "@launchql/totp": 151,
      "@pgql/parse": 64,
      "@pgsql/enums": 23,
      "@pgsql/parser": 4055,
      "@pgsql/types": 127153,
      "@pgsql/utils": 32919,
      "@pyramation/postgraphile-plugin-fulltext-filter": 2244,
      "graphile-column-privileges-mutations": 123,
      "libpg-query": 139620,
      "pg-proto-parser": 76,
      "pg-query-native-latest": 10,
      "pg-utils": 48,
      "pgsql-deparser": 114397,
      "pgsql-enums": 114356,
      "pgsql-parser": 81836
    }
  },
  "protobufs": {
    "total": 112570,
    "packages": {
      "@protobufs/cosmos": 4167,
      "@protobufs/google": 5106,
      "@protobufs/gogoproto": 5087,
      "@protobufs/cosmwasm": 815,
      "@protobufs/tendermint": 4150,
      "@protobufs/ibc": 1100,
      "@protobufs/cosmos_proto": 4127,
      "@protobufs/osmosis": 423,
      "@protobufs/secret": 30,
      "@protobufs/juno": 50,
      "@protobufs/akash": 25,
      "@protobufs/regen": 26,
      "@protobufs/pylons": 21,
      "@protobufs/stargaze": 42,
      "@protobufs/bcna": 19,
      "@protobufs/comdex": 20,
      "@protobufs/evmos": 16,
      "@protobufs/axelar": 17,
      "@protobufs/amino": 1107,
      "@cosmology/protobufjs": 82622,
      "@pyramation/protobufjs": 3600
    }
  },
  "utils": {
    "total": null,
    "packages": {
      "ast-stringify": 53060,
      "nested-obj": 34065,
      "schema-typescript": 760,
      "etag-hash": 1096,
      "uuid-hash": 436,
      "inquirerer": 54066,
      "publish-scripts": 442,
      "skitch-template": 97
    }
  }
}