{
  "cosmos-kit": {
    "total": 1232271,
    "packages": {
      "cosmos-kit": 37472,
      "@cosmos-kit/core": 511258,
      "@cosmos-kit/react": 146904,
      "@cosmos-kit/react-lite": 174559,
      "@cosmos-kit/walletconnect": 362078
    }
  },
  "cosmos-kit-wallets": {
    "total": 5641630,
    "packages": {
      "@cosmos-kit/frontier-extension": 54276,
      "@cosmos-kit/ledger": 51099,
      "@cosmos-kit/cosmos-extension-metamask": 27433,
      "@cosmos-kit/fin": 44991,
      "@cosmos-kit/coin98-extension": 52111,
      "@cosmos-kit/okxwallet-extension": 196525,
      "@cosmos-kit/trust-mobile": 161984,
      "@cosmos-kit/shell": 46983,
      "@cosmos-kit/leap-capsule-social-login": 3688,
      "@cosmos-kit/cosmostation-extension": 281676,
      "@cosmos-kit/vectis": 69736,
      "@cosmos-kit/fin-extension": 50302,
      "@cosmos-kit/ninji": 9212,
      "@cosmos-kit/station-extension": 196932,
      "@cosmos-kit/coin98": 52321,
      "@cosmos-kit/leap-extension": 330151,
      "@cosmos-kit/exodus": 45184,
      "@cosmos-kit/trust-extension": 152155,
      "@cosmos-kit/leap": 310731,
      "@cosmos-kit/xdefi": 196121,
      "@cosmos-kit/web3auth": 23946,
      "@cosmos-kit/initia-extension": 4804,
      "@cosmos-kit/cosmostation": 265223,
      "@cosmos-kit/shell-extension": 47472,
      "@cosmos-kit/cosmostation-mobile": 259344,
      "@cosmos-kit/vectis-extension": 68558,
      "@cosmos-kit/station": 196742,
      "@cosmos-kit/exodus-extension": 46020,
      "@cosmos-kit/leap-mobile": 292870,
      "@cosmos-kit/initia": 4598,
      "@cosmos-kit/frontier": 53011,
      "@cosmos-kit/trust": 162029,
      "@cosmos-kit/compass": 56640,
      "@cosmos-kit/keplr-mobile": 326098,
      "@cosmos-kit/keplr-extension": 345682,
      "@cosmos-kit/ninji-extension": 9886,
      "@cosmos-kit/compass-extension": 62854,
      "@cosmos-kit/xdefi-extension": 215844,
      "@cosmos-kit/okxwallet": 167896,
      "@cosmos-kit/omni": 58012,
      "@cosmos-kit/keplr": 330506,
      "@cosmos-kit/omni-mobile": 60296,
      "@cosmos-kit/leap-metamask-cosmos-snap": 249688
    }
  },
  "cosmwasm": {
    "total": 1630286,
    "packages": {
      "@cosmwasm/ts-codegen": 794909,
      "@cosmwasm/ts-codegen-types": 38641,
      "@cosmwasm/ts-codegen-ast": 38860,
      "wasm-ast-types": 753031,
      "cosmwasm-typescript-gen": 4845
    }
  },
  "interchain-ui": {
    "total": 132607,
    "packages": {
      "@interchain-ui/react": 125177,
      "@interchain-ui/vue": 7430
    }
  },
  "telescope": {
    "total": 3900721,
    "packages": {
      "@cosmology/telescope": 239642,
      "@cosmology/lcd": 239385,
      "@cosmology/ast": 249668,
      "@cosmology/types": 277893,
      "@cosmology/utils": 278083,
      "@cosmology/proto-parser": 277343,
      "@osmonauts/telescope": 288169,
      "@osmonauts/lcd": 908096,
      "@osmonauts/ast": 283345,
      "@osmonauts/utils": 268764,
      "@osmonauts/types": 294258,
      "@osmonauts/proto-parser": 296075
    }
  },
  "dydx": {
    "total": 63047,
    "packages": {
      "@dydxprotocol/v4-client-js": 63047
    }
  },
  "stargaze": {
    "total": 18186,
    "packages": {
      "stargazejs": 14340,
      "@stargaze-zone/chain": 951,
      "@stargaze-zone/contracts": 1239,
      "stargaze-query": 1656
    }
  },
  "stride": {
    "total": 23598,
    "packages": {
      "stridejs": 23598
    }
  },
  "quicksilver": {
    "total": 4388,
    "packages": {
      "quicksilverjs": 4388
    }
  },
  "juno": {
    "total": 21063,
    "packages": {
      "juno-network": 18430,
      "@juno-network/assets": 2633
    }
  },
  "osmosis": {
    "total": 352614,
    "packages": {
      "@osmonauts/math": 26734,
      "osmojs": 309749,
      "osmo-query": 16131
    }
  },
  "chain-registry": {
    "total": 4053338,
    "packages": {
      "@chain-registry/client": 289810,
      "@chain-registry/types": 1465925,
      "@chain-registry/keplr": 576449,
      "@chain-registry/cosmostation": 454566,
      "@chain-registry/osmosis": 77458,
      "@chain-registry/juno": 29451,
      "@chain-registry/assets": 44826,
      "@chain-registry/utils": 415656,
      "chain-registry": 699197
    }
  },
  "cosmology": {
    "total": 122710,
    "packages": {
      "cosmjs-utils": 22108,
      "@cosmology/cli": 9530,
      "@cosmology/core": 20730,
      "cosmology": 9154,
      "interchain": 15763,
      "interchain-query": 13905,
      "create-cosmos-app": 7438,
      "create-cosmwasm-app": 2357,
      "@cosmology-ui/react": 21725
    }
  },
  "starship": {
    "total": 15603,
    "packages": {
      "starshipjs": 5465,
      "@starship-ci/cli": 4850,
      "@starship-ci/client": 5288
    }
  },
  "launchql": {
    "total": null,
    "packages": {
      "@launchql/db-templates": 3449,
      "@launchql/db-transform": 1554,
      "@launchql/ext-achievements": 1867,
      "@launchql/ext-jobs-queue": 2311,
      "@launchql/ext-jwt-claims": 2001,
      "@launchql/ext-types": 2446,
      "@launchql/faker": 1988,
      "@launchql/inflection": 2192,
      "@launchql/totp": 1995,
      "@pgql/parse": 56515,
      "@pgsql/enums": 838,
      "@pgsql/parser": 779,
      "@pgsql/types": 376880,
      "@pgsql/utils": 28805,
      "@pyramation/postgraphile-plugin-fulltext-filter": 32389,
      "graphile-column-privileges-mutations": 2772,
      "libpg-query": 3178945,
      "pg-proto-parser": 4449,
      "pg-query-native-latest": 395,
      "pg-utils": 611,
      "pgsql-deparser": 2666235,
      "pgsql-enums": 2731796,
      "pgsql-parser": 2646540
    }
  },
  "protobufs": {
    "total": 2983629,
    "packages": {
      "@protobufs/cosmos": 367931,
      "@protobufs/google": 378290,
      "@protobufs/gogoproto": 378210,
      "@protobufs/cosmwasm": 139870,
      "@protobufs/tendermint": 365028,
      "@protobufs/ibc": 142140,
      "@protobufs/cosmos_proto": 369638,
      "@protobufs/osmosis": 10584,
      "@protobufs/secret": 472,
      "@protobufs/juno": 1561,
      "@protobufs/akash": 638,
      "@protobufs/regen": 595,
      "@protobufs/pylons": 405,
      "@protobufs/stargaze": 638,
      "@protobufs/bcna": 519,
      "@protobufs/comdex": 432,
      "@protobufs/evmos": 302,
      "@protobufs/axelar": 272,
      "@protobufs/amino": 144577,
      "@cosmology/protobufjs": 412481,
      "@pyramation/protobufjs": 269046
    }
  },
  "utils": {
    "total": null,
    "packages": {
      "ast-stringify": 648196,
      "nested-obj": 67053,
      "schema-typescript": 8791,
      "etag-hash": 46568,
      "uuid-hash": 14194,
      "inquirerer": 662375,
      "publish-scripts": 15243,
      "skitch-template": 1412
    }
  }
}