{
  "cosmos-kit": {
    "total": 736884,
    "packages": {
      "cosmos-kit": 18589,
      "@cosmos-kit/core": 311553,
      "@cosmos-kit/react": 108087,
      "@cosmos-kit/react-lite": 107795,
      "@cosmos-kit/walletconnect": 190860
    }
  },
  "cosmos-kit-wallets": {
    "total": 2565939,
    "packages": {
      "@cosmos-kit/frontier-extension": 33455,
      "@cosmos-kit/ledger": 25335,
      "@cosmos-kit/cosmos-extension-metamask": 17360,
      "@cosmos-kit/fin": 22206,
      "@cosmos-kit/coin98-extension": 29153,
      "@cosmos-kit/okxwallet-extension": 60723,
      "@cosmos-kit/trust-mobile": 39955,
      "@cosmos-kit/shell": 24585,
      "@cosmos-kit/leap-capsule-social-login": 820,
      "@cosmos-kit/cosmostation-extension": 133359,
      "@cosmos-kit/vectis": 43845,
      "@cosmos-kit/fin-extension": 26516,
      "@cosmos-kit/ninji": 4567,
      "@cosmos-kit/station-extension": 57617,
      "@cosmos-kit/coin98": 29452,
      "@cosmos-kit/leap-extension": 169205,
      "@cosmos-kit/exodus": 22906,
      "@cosmos-kit/trust-extension": 29995,
      "@cosmos-kit/leap": 167906,
      "@cosmos-kit/xdefi": 66379,
      "@cosmos-kit/web3auth": 18027,
      "@cosmos-kit/initia-extension": 2637,
      "@cosmos-kit/cosmostation": 137518,
      "@cosmos-kit/shell-extension": 25044,
      "@cosmos-kit/cosmostation-mobile": 125468,
      "@cosmos-kit/vectis-extension": 42443,
      "@cosmos-kit/station": 57419,
      "@cosmos-kit/exodus-extension": 23276,
      "@cosmos-kit/leap-mobile": 133381,
      "@cosmos-kit/initia": 2531,
      "@cosmos-kit/frontier": 32068,
      "@cosmos-kit/trust": 41536,
      "@cosmos-kit/compass": 32456,
      "@cosmos-kit/keplr-mobile": 170560,
      "@cosmos-kit/keplr-extension": 178066,
      "@cosmos-kit/ninji-extension": 4836,
      "@cosmos-kit/compass-extension": 37719,
      "@cosmos-kit/xdefi-extension": 85712,
      "@cosmos-kit/okxwallet": 49855,
      "@cosmos-kit/omni": 38136,
      "@cosmos-kit/keplr": 187619,
      "@cosmos-kit/omni-mobile": 39888,
      "@cosmos-kit/leap-metamask-cosmos-snap": 94405
    }
  },
  "cosmwasm": {
    "total": 863027,
    "packages": {
      "@cosmwasm/ts-codegen": 432245,
      "@cosmwasm/ts-codegen-types": 624,
      "@cosmwasm/ts-codegen-ast": 582,
      "wasm-ast-types": 429576
    }
  },
  "interchain-ui": {
    "total": 63732,
    "packages": {
      "@interchain-ui/react": 63732
    }
  },
  "telescope": {
    "total": 1377649,
    "packages": {
      "@cosmology/telescope": 84298,
      "@cosmology/lcd": 85043,
      "@cosmology/ast": 83483,
      "@cosmology/types": 80064,
      "@osmonauts/telescope": 216460,
      "@osmonauts/lcd": 618218,
      "@osmonauts/ast": 210083
    }
  },
  "dydx": {
    "total": 26759,
    "packages": {
      "@dydxprotocol/v4-client-js": 26759
    }
  },
  "stargaze": {
    "total": 17428,
    "packages": {
      "stargazejs": 13346,
      "@stargaze-zone/chain": 1227,
      "@stargaze-zone/contracts": 1612,
      "stargaze-query": 1243
    }
  },
  "stride": {
    "total": 21298,
    "packages": {
      "stridejs": 21298
    }
  },
  "quicksilver": {
    "total": 4166,
    "packages": {
      "quicksilverjs": 4166
    }
  },
  "juno": {
    "total": 20275,
    "packages": {
      "juno-network": 16522,
      "@juno-network/assets": 3753
    }
  },
  "osmosis": {
    "total": 235386,
    "packages": {
      "@osmonauts/math": 14943,
      "osmojs": 220443
    }
  },
  "chain-registry": {
    "total": 1841769,
    "packages": {
      "@chain-registry/client": 55247,
      "@chain-registry/types": 766579,
      "@chain-registry/keplr": 199359,
      "@chain-registry/cosmostation": 162684,
      "@chain-registry/osmosis": 46148,
      "@chain-registry/juno": 14727,
      "@chain-registry/assets": 27494,
      "@chain-registry/utils": 171276,
      "chain-registry": 398255
    }
  },
  "cosmology": {
    "total": 77805,
    "packages": {
      "@cosmology/cli": 11860,
      "@cosmology/core": 22698,
      "cosmology": 12516,
      "interchain": 12840,
      "interchain-query": 10349,
      "create-cosmos-app": 7542
    }
  },
  "starship": {
    "total": 4597,
    "packages": {
      "starshipjs": 1336,
      "@starship-ci/cli": 1499,
      "@starship-ci/client": 1762
    }
  },
  "launchql": {
    "total": null,
    "packages": {
      "pg-proto-parser": 3373,
      "@pgsql/parser": 145,
      "@pgsql/enums": 685,
      "@pgsql/types": 23541,
      "@pgsql/utils": 929,
      "@pgql/parse": 75355,
      "libpg-query": 2668460,
      "pgsql-parser": 2375412,
      "pgsql-enums": 2597541,
      "pgsql-deparser": 2369868
    }
  },
  "protobufs": {
    "total": 1440549,
    "packages": {
      "@protobufs/cosmos": 232003,
      "@protobufs/google": 238017,
      "@protobufs/gogoproto": 237855,
      "@protobufs/cosmwasm": 80397,
      "@protobufs/tendermint": 231764,
      "@protobufs/ibc": 81481,
      "@protobufs/cosmos_proto": 236413,
      "@protobufs/osmosis": 12374,
      "@protobufs/secret": 537,
      "@protobufs/juno": 1929,
      "@protobufs/akash": 914,
      "@protobufs/regen": 804,
      "@protobufs/pylons": 630,
      "@protobufs/stargaze": 900,
      "@protobufs/bcna": 724,
      "@protobufs/comdex": 632,
      "@protobufs/evmos": 498,
      "@protobufs/axelar": 474,
      "@protobufs/amino": 82203
    }
  },
  "utils": {
    "total": null,
    "packages": {
      "ast-stringify": 351651,
      "nested-obj": 1200,
      "schema-typescript": 2080,
      "etag-hash": 38965
    }
  }
}