{
  "cosmos-kit": {
    "total": 858820,
    "packages": {
      "cosmos-kit": 22627,
      "@cosmos-kit/core": 365168,
      "@cosmos-kit/react": 117817,
      "@cosmos-kit/react-lite": 125520,
      "@cosmos-kit/walletconnect": 227688
    }
  },
  "cosmos-kit-wallets": {
    "total": 3098615,
    "packages": {
      "@cosmos-kit/frontier-extension": 39173,
      "@cosmos-kit/ledger": 31113,
      "@cosmos-kit/cosmos-extension-metamask": 21216,
      "@cosmos-kit/fin": 27596,
      "@cosmos-kit/coin98-extension": 34906,
      "@cosmos-kit/okxwallet-extension": 80696,
      "@cosmos-kit/trust-mobile": 56972,
      "@cosmos-kit/shell": 29896,
      "@cosmos-kit/leap-capsule-social-login": 1310,
      "@cosmos-kit/cosmostation-extension": 158447,
      "@cosmos-kit/vectis": 49536,
      "@cosmos-kit/fin-extension": 32259,
      "@cosmos-kit/ninji": 6494,
      "@cosmos-kit/station-extension": 78774,
      "@cosmos-kit/coin98": 35123,
      "@cosmos-kit/leap-extension": 197919,
      "@cosmos-kit/exodus": 28172,
      "@cosmos-kit/trust-extension": 46741,
      "@cosmos-kit/leap": 191112,
      "@cosmos-kit/xdefi": 85538,
      "@cosmos-kit/web3auth": 20415,
      "@cosmos-kit/initia-extension": 3358,
      "@cosmos-kit/cosmostation": 157294,
      "@cosmos-kit/shell-extension": 30372,
      "@cosmos-kit/cosmostation-mobile": 147578,
      "@cosmos-kit/vectis-extension": 48772,
      "@cosmos-kit/station": 78541,
      "@cosmos-kit/exodus-extension": 28755,
      "@cosmos-kit/leap-mobile": 159491,
      "@cosmos-kit/initia": 3209,
      "@cosmos-kit/frontier": 37566,
      "@cosmos-kit/trust": 57411,
      "@cosmos-kit/compass": 38288,
      "@cosmos-kit/keplr-mobile": 199585,
      "@cosmos-kit/keplr-extension": 209357,
      "@cosmos-kit/ninji-extension": 6752,
      "@cosmos-kit/compass-extension": 43890,
      "@cosmos-kit/xdefi-extension": 106001,
      "@cosmos-kit/okxwallet": 66413,
      "@cosmos-kit/omni": 43884,
      "@cosmos-kit/keplr": 212845,
      "@cosmos-kit/omni-mobile": 45764,
      "@cosmos-kit/leap-metamask-cosmos-snap": 120081
    }
  },
  "cosmwasm": {
    "total": 1074130,
    "packages": {
      "@cosmwasm/ts-codegen": 534958,
      "@cosmwasm/ts-codegen-types": 2415,
      "@cosmwasm/ts-codegen-ast": 2431,
      "wasm-ast-types": 529950,
      "cosmwasm-typescript-gen": 4376
    }
  },
  "interchain-ui": {
    "total": 83555,
    "packages": {
      "@interchain-ui/react": 77724,
      "@interchain-ui/vue": 5831
    }
  },
  "telescope": {
    "total": 2577743,
    "packages": {
      "@cosmology/telescope": 113848,
      "@cosmology/lcd": 118480,
      "@cosmology/ast": 112476,
      "@cosmology/types": 108845,
      "@cosmology/utils": 108622,
      "@cosmology/proto-parser": 108220,
      "@osmonauts/telescope": 241551,
      "@osmonauts/lcd": 714638,
      "@osmonauts/ast": 235252,
      "@osmonauts/utils": 221072,
      "@osmonauts/types": 246388,
      "@osmonauts/proto-parser": 248351
    }
  },
  "dydx": {
    "total": 34939,
    "packages": {
      "@dydxprotocol/v4-client-js": 34939
    }
  },
  "stargaze": {
    "total": 18056,
    "packages": {
      "stargazejs": 13929,
      "@stargaze-zone/chain": 1163,
      "@stargaze-zone/contracts": 1558,
      "stargaze-query": 1406
    }
  },
  "stride": {
    "total": 22683,
    "packages": {
      "stridejs": 22683
    }
  },
  "quicksilver": {
    "total": 4300,
    "packages": {
      "quicksilverjs": 4300
    }
  },
  "juno": {
    "total": 21451,
    "packages": {
      "juno-network": 17888,
      "@juno-network/assets": 3563
    }
  },
  "osmosis": {
    "total": 276544,
    "packages": {
      "@osmonauts/math": 18112,
      "osmojs": 250888,
      "osmo-query": 7544
    }
  },
  "chain-registry": {
    "total": 2258652,
    "packages": {
      "@chain-registry/client": 99018,
      "@chain-registry/types": 905292,
      "@chain-registry/keplr": 261329,
      "@chain-registry/cosmostation": 208431,
      "@chain-registry/osmosis": 55056,
      "@chain-registry/juno": 18801,
      "@chain-registry/assets": 30424,
      "@chain-registry/utils": 223966,
      "chain-registry": 456335
    }
  },
  "cosmology": {
    "total": 129258,
    "packages": {
      "cosmjs-utils": 21728,
      "@cosmology/cli": 11354,
      "@cosmology/core": 22379,
      "cosmology": 11684,
      "interchain": 14229,
      "interchain-query": 11057,
      "create-cosmos-app": 7931,
      "create-cosmwasm-app": 2653,
      "@cosmology-ui/react": 26243
    }
  },
  "starship": {
    "total": 8377,
    "packages": {
      "starshipjs": 2104,
      "@starship-ci/cli": 2997,
      "@starship-ci/client": 3276
    }
  },
  "launchql": {
    "total": null,
    "packages": {
      "@launchql/db-templates": 2958,
      "@launchql/db-transform": 1328,
      "@launchql/ext-achievements": 1686,
      "@launchql/ext-jobs-queue": 1801,
      "@launchql/ext-jwt-claims": 1776,
      "@launchql/ext-types": 2061,
      "@launchql/faker": 1682,
      "@launchql/inflection": 1954,
      "@launchql/totp": 1723,
      "@pgql/parse": 70147,
      "@pgsql/enums": 748,
      "@pgsql/parser": 173,
      "@pgsql/types": 99292,
      "@pgsql/utils": 1012,
      "@pyramation/postgraphile-plugin-fulltext-filter": 29491,
      "graphile-column-privileges-mutations": 2629,
      "libpg-query": 2925899,
      "pg-proto-parser": 3945,
      "pg-query-native-latest": 387,
      "pg-utils": 581,
      "pgsql-deparser": 2566733,
      "pgsql-enums": 2773229,
      "pgsql-parser": 2574360
    }
  },
  "protobufs": {
    "total": 2177489,
    "packages": {
      "@protobufs/cosmos": 280146,
      "@protobufs/google": 286277,
      "@protobufs/gogoproto": 286157,
      "@protobufs/cosmwasm": 103818,
      "@protobufs/tendermint": 279184,
      "@protobufs/ibc": 105135,
      "@protobufs/cosmos_proto": 283828,
      "@protobufs/osmosis": 11920,
      "@protobufs/secret": 522,
      "@protobufs/juno": 1796,
      "@protobufs/akash": 744,
      "@protobufs/regen": 658,
      "@protobufs/pylons": 489,
      "@protobufs/stargaze": 748,
      "@protobufs/bcna": 586,
      "@protobufs/comdex": 499,
      "@protobufs/evmos": 362,
      "@protobufs/axelar": 335,
      "@protobufs/amino": 106761,
      "@cosmology/protobufjs": 207968,
      "@pyramation/protobufjs": 219556
    }
  },
  "utils": {
    "total": null,
    "packages": {
      "ast-stringify": 428854,
      "nested-obj": 3126,
      "schema-typescript": 3685,
      "etag-hash": 41931,
      "uuid-hash": 13630,
      "inquirerer": 437697,
      "publish-scripts": 12846,
      "skitch-template": 1253
    }
  }
}