{
  "cosmos-kit": {
    "total": 13569,
    "packages": {
      "cosmos-kit": 401,
      "@cosmos-kit/core": 6187,
      "@cosmos-kit/react": 1135,
      "@cosmos-kit/react-lite": 1867,
      "@cosmos-kit/walletconnect": 3979
    }
  },
  "cosmos-kit-wallets": {
    "total": 60573,
    "packages": {
      "@cosmos-kit/frontier-extension": 542,
      "@cosmos-kit/ledger": 672,
      "@cosmos-kit/cosmos-extension-metamask": 940,
      "@cosmos-kit/fin": 661,
      "@cosmos-kit/coin98-extension": 593,
      "@cosmos-kit/okxwallet-extension": 1886,
      "@cosmos-kit/trust-mobile": 622,
      "@cosmos-kit/shell": 589,
      "@cosmos-kit/leap-capsule-social-login": 22,
      "@cosmos-kit/cosmostation-extension": 2765,
      "@cosmos-kit/vectis": 632,
      "@cosmos-kit/fin-extension": 721,
      "@cosmos-kit/ninji": 241,
      "@cosmos-kit/station-extension": 2247,
      "@cosmos-kit/coin98": 629,
      "@cosmos-kit/leap-extension": 3893,
      "@cosmos-kit/exodus": 532,
      "@cosmos-kit/trust-extension": 609,
      "@cosmos-kit/leap": 3611,
      "@cosmos-kit/xdefi": 1917,
      "@cosmos-kit/web3auth": 188,
      "@cosmos-kit/initia-extension": 49,
      "@cosmos-kit/cosmostation": 2627,
      "@cosmos-kit/shell-extension": 591,
      "@cosmos-kit/cosmostation-mobile": 2608,
      "@cosmos-kit/vectis-extension": 613,
      "@cosmos-kit/station": 2293,
      "@cosmos-kit/exodus-extension": 535,
      "@cosmos-kit/leap-mobile": 3572,
      "@cosmos-kit/initia": 48,
      "@cosmos-kit/frontier": 545,
      "@cosmos-kit/trust": 643,
      "@cosmos-kit/compass": 654,
      "@cosmos-kit/keplr-mobile": 3796,
      "@cosmos-kit/keplr-extension": 4030,
      "@cosmos-kit/ninji-extension": 255,
      "@cosmos-kit/compass-extension": 726,
      "@cosmos-kit/xdefi-extension": 2229,
      "@cosmos-kit/okxwallet": 1494,
      "@cosmos-kit/omni": 662,
      "@cosmos-kit/keplr": 3769,
      "@cosmos-kit/omni-mobile": 672,
      "@cosmos-kit/leap-metamask-cosmos-snap": 3650
    }
  },
  "cosmwasm": {
    "total": 21235,
    "packages": {
      "@cosmwasm/ts-codegen": 21235
    }
  },
  "interchain-ui": {
    "total": 1477,
    "packages": {
      "@interchain-ui/react": 1477
    }
  },
  "telescope": {
    "total": 34033,
    "packages": {
      "@cosmology/telescope": 2876,
      "@cosmology/lcd": 3165,
      "@cosmology/ast": 2767,
      "@osmonauts/telescope": 4348,
      "@osmonauts/lcd": 16506,
      "@osmonauts/ast": 4371
    }
  },
  "dydx": {
    "total": 1926,
    "packages": {
      "@dydxprotocol/v4-client-js": 1926
    }
  },
  "stargaze": {
    "total": 347,
    "packages": {
      "stargazejs": 125,
      "@stargaze-zone/chain": 47,
      "@stargaze-zone/contracts": 41,
      "stargaze-query": 134
    }
  },
  "stride": {
    "total": 351,
    "packages": {
      "stridejs": 351
    }
  },
  "quicksilver": {
    "total": 68,
    "packages": {
      "quicksilverjs": 68
    }
  },
  "juno": {
    "total": 178,
    "packages": {
      "juno-network": 174,
      "@juno-network/assets": 4
    }
  },
  "osmosis": {
    "total": 4441,
    "packages": {
      "@osmonauts/math": 208,
      "osmojs": 4233
    }
  },
  "chain-registry": {
    "total": 49940,
    "packages": {
      "@chain-registry/client": 2909,
      "@chain-registry/types": 16888,
      "@chain-registry/keplr": 4829,
      "@chain-registry/cosmostation": 5613,
      "@chain-registry/osmosis": 897,
      "@chain-registry/juno": 410,
      "@chain-registry/assets": 556,
      "@chain-registry/utils": 5034,
      "chain-registry": 12804
    }
  },
  "cosmology": {
    "total": 1330,
    "packages": {
      "@cosmology/cli": 18,
      "@cosmology/core": 345,
      "cosmology": 13,
      "create-cosmos-app": 370,
      "interchain": 48,
      "interchain-query": 166
    }
  },
  "launchql": {
    "total": 75012,
    "packages": {
      "libpg-query": 21871,
      "pgsql-parser": 17815,
      "pgsql-enums": 17594,
      "pgsql-deparser": 17732
    }
  },
  "protobufs": {
    "total": 77487,
    "packages": {
      "@protobufs/cosmos": 11201,
      "@protobufs/google": 11291,
      "@protobufs/gogoproto": 11291,
      "@protobufs/cosmwasm": 6976,
      "@protobufs/tendermint": 11173,
      "@protobufs/ibc": 6977,
      "@protobufs/cosmos_proto": 11219,
      "@protobufs/osmosis": 158,
      "@protobufs/secret": 0,
      "@protobufs/juno": 5,
      "@protobufs/akash": 1,
      "@protobufs/regen": 1,
      "@protobufs/pylons": 1,
      "@protobufs/stargaze": 1,
      "@protobufs/bcna": 1,
      "@protobufs/comdex": 1,
      "@protobufs/evmos": 1,
      "@protobufs/axelar": 1,
      "@protobufs/amino": 7188
    }
  }
}