{
  "hyperwebjs": {
    "total": 28,
    "packages": {
      "create-hyperweb-app": 9,
      "@hyperweb/cli": 1,
      "hyperwebjs": 12,
      "hyperweb-kit": 1,
      "@hyperweb/build": 4,
      "@hyperweb/ts-json-schema": 1
    }
  },
  "interchain-js": {
    "total": 4564,
    "packages": {
      "interchainjs": 682,
      "injectivejs": 171,
      "@interchainjs/utils": 571,
      "@interchainjs/types": 599,
      "@interchainjs/auth": 552,
      "@interchainjs/cosmos": 503,
      "@interchainjs/cosmos-msgs": 6,
      "@interchainjs/cosmos-query": 6,
      "@interchainjs/ethereum": 272,
      "@interchainjs/injective": 185,
      "@interchainjs/cosmos-types": 733,
      "@interchainjs/ethermint": 5,
      "injective-query": 2,
      "injective-react": 152,
      "injective-vue": 114,
      "interchain-react": 11
    }
  },
  "cosmos-kit": {
    "total": 18540,
    "packages": {
      "interchain-kit": 54,
      "@interchain-kit/core": 176,
      "@interchain-kit/react": 178,
      "@interchain-kit/vue": 44,
      "cosmos-kit": 727,
      "@cosmos-kit/core": 7812,
      "@cosmos-kit/react": 1580,
      "@cosmos-kit/react-lite": 1944,
      "@cosmos-kit/walletconnect": 6025
    }
  },
  "create-cosmos-app": {
    "total": 104,
    "packages": {
      "create-cosmos-app": 89,
      "create-interchain-app": 15
    }
  },
  "interchain-kit": {
    "total": 452,
    "packages": {
      "interchain-kit": 54,
      "@interchain-kit/core": 176,
      "@interchain-kit/react": 178,
      "@interchain-kit/vue": 44
    }
  },
  "interchain-kit-wallets": {
    "total": 1182,
    "packages": {
      "@interchain-kit/okx-extension": 52,
      "@interchain-kit/mock-wallet": 79,
      "@interchain-kit/leap-extension": 68,
      "@interchain-kit/ledger": 107,
      "@interchain-kit/coin98-extension": 56,
      "@interchain-kit/leap-mobile": 56,
      "@interchain-kit/keplr-mobile": 115,
      "@interchain-kit/keplr-extension": 123,
      "@interchain-kit/frontier-extension": 53,
      "@interchain-kit/station-extension": 92,
      "@interchain-kit/cosmostation-extension": 53,
      "@interchain-kit/galaxy-station-extension": 55,
      "@interchain-kit/vue": 44,
      "@interchain-kit/cosmos-extension-metamask": 74,
      "@interchain-kit/trust-extension": 64,
      "@interchain-kit/leap-cosmos-extension-metamask": 67,
      "@interchain-kit/xdefi-extension": 24
    }
  },
  "cosmos-kit-wallets": {
    "total": 101069,
    "packages": {
      "@interchain-kit/okx-extension": 52,
      "@interchain-kit/mock-wallet": 79,
      "@interchain-kit/leap-extension": 68,
      "@interchain-kit/ledger": 107,
      "@interchain-kit/coin98-extension": 56,
      "@interchain-kit/leap-mobile": 56,
      "@interchain-kit/keplr-mobile": 115,
      "@interchain-kit/keplr-extension": 123,
      "@interchain-kit/frontier-extension": 53,
      "@interchain-kit/station-extension": 92,
      "@interchain-kit/cosmostation-extension": 53,
      "@interchain-kit/galaxy-station-extension": 55,
      "@interchain-kit/vue": 44,
      "@interchain-kit/cosmos-extension-metamask": 74,
      "@interchain-kit/trust-extension": 64,
      "@interchain-kit/leap-cosmos-extension-metamask": 67,
      "@interchain-kit/xdefi-extension": 24,
      "@cosmos-kit/frontier-extension": 440,
      "@cosmos-kit/ledger": 904,
      "@cosmos-kit/cosmos-extension-metamask": 713,
      "@cosmos-kit/fin": 791,
      "@cosmos-kit/coin98-extension": 844,
      "@cosmos-kit/okxwallet-extension": 4035,
      "@cosmos-kit/trust-mobile": 4046,
      "@cosmos-kit/shell": 764,
      "@cosmos-kit/leap-capsule-social-login": 141,
      "@cosmos-kit/cosmostation-extension": 4686,
      "@cosmos-kit/vectis": 430,
      "@cosmos-kit/fin-extension": 850,
      "@cosmos-kit/ninji": 194,
      "@cosmos-kit/station-extension": 3750,
      "@cosmos-kit/coin98": 804,
      "@cosmos-kit/leap-extension": 5509,
      "@cosmos-kit/exodus": 771,
      "@cosmos-kit/trust-extension": 3940,
      "@cosmos-kit/leap": 5433,
      "@cosmos-kit/xdefi": 3628,
      "@cosmos-kit/web3auth": 220,
      "@cosmos-kit/initia-extension": 141,
      "@cosmos-kit/cosmostation": 4509,
      "@cosmos-kit/shell-extension": 859,
      "@cosmos-kit/cosmostation-mobile": 4589,
      "@cosmos-kit/vectis-extension": 449,
      "@cosmos-kit/station": 3675,
      "@cosmos-kit/exodus-extension": 822,
      "@cosmos-kit/leap-mobile": 5324,
      "@cosmos-kit/initia": 119,
      "@cosmos-kit/frontier": 434,
      "@cosmos-kit/trust": 3904,
      "@cosmos-kit/compass": 793,
      "@cosmos-kit/keplr-mobile": 5393,
      "@cosmos-kit/keplr-extension": 5516,
      "@cosmos-kit/ninji-extension": 201,
      "@cosmos-kit/compass-extension": 881,
      "@cosmos-kit/xdefi-extension": 3687,
      "@cosmos-kit/okxwallet": 3374,
      "@cosmos-kit/omni": 782,
      "@cosmos-kit/keplr": 5276,
      "@cosmos-kit/omni-mobile": 850,
      "@cosmos-kit/leap-metamask-cosmos-snap": 5416
    }
  },
  "cosmwasm": {
    "total": 18301,
    "packages": {
      "@cosmwasm/ts-codegen": 8938,
      "@cosmwasm/ts-codegen-types": 283,
      "@cosmwasm/ts-codegen-ast": 309,
      "wasm-ast-types": 8637,
      "cosmwasm-typescript-gen": 134
    }
  },
  "interchain-ui": {
    "total": 1655,
    "packages": {
      "@interchain-ui/react": 1638,
      "@interchain-ui/vue": 17
    }
  },
  "telescope": {
    "total": 82811,
    "packages": {
      "@cosmology/telescope": 4770,
      "@cosmology/lcd": 20194,
      "@cosmology/ast": 7837,
      "@cosmology/types": 10602,
      "@cosmology/utils": 10625,
      "@cosmology/proto-parser": 10581,
      "@osmonauts/telescope": 902,
      "@osmonauts/lcd": 13629,
      "@osmonauts/ast": 918,
      "@osmonauts/utils": 905,
      "@osmonauts/types": 958,
      "@osmonauts/proto-parser": 890
    }
  },
  "dydx": {
    "total": 6641,
    "packages": {
      "@dydxprotocol/v4-client-js": 6641
    }
  },
  "stargaze": {
    "total": 119,
    "packages": {
      "stargazejs": 85,
      "@stargaze-zone/chain": 9,
      "@stargaze-zone/contracts": 8,
      "stargaze-query": 17
    }
  },
  "stride": {
    "total": 68,
    "packages": {
      "stridejs": 68
    }
  },
  "quicksilver": {
    "total": 34,
    "packages": {
      "quicksilverjs": 34
    }
  },
  "juno": {
    "total": 249,
    "packages": {
      "juno-network": 215,
      "@juno-network/assets": 34
    }
  },
  "osmosis": {
    "total": 3608,
    "packages": {
      "@osmonauts/math": 373,
      "osmojs": 2950,
      "osmo-query": 285
    }
  },
  "chain-registry": {
    "total": 117588,
    "packages": {
      "@chain-registry/client": 10616,
      "@chain-registry/types": 40427,
      "@chain-registry/keplr": 12817,
      "@chain-registry/cosmostation": 9774,
      "@chain-registry/osmosis": 780,
      "@chain-registry/juno": 906,
      "@chain-registry/assets": 1124,
      "@chain-registry/utils": 20994,
      "chain-registry": 20150
    }
  },
  "cosmology": {
    "total": 8283,
    "packages": {
      "cosmjs-utils": 148,
      "@cosmology/cli": 31,
      "@cosmology/core": 63,
      "cosmology": 53,
      "interchain": 7779,
      "interchain-query": 64,
      "create-cosmos-app": 89,
      "create-cosmwasm-app": 42,
      "@cosmology-ui/react": 14
    }
  },
  "starship": {
    "total": 571,
    "packages": {
      "starshipjs": 314,
      "@starship-ci/cli": 124,
      "@starship-ci/client": 133
    }
  },
  "launchql": {
    "total": null,
    "packages": {
      "@launchql/db-templates": 76,
      "@launchql/db-transform": 34,
      "@launchql/ext-achievements": 40,
      "@launchql/ext-jobs-queue": 43,
      "@launchql/ext-jwt-claims": 42,
      "@launchql/ext-types": 52,
      "@launchql/faker": 44,
      "@launchql/inflection": 48,
      "@launchql/totp": 90,
      "@pgql/parse": 18,
      "@pgsql/enums": 7,
      "@pgsql/parser": 572,
      "@pgsql/types": 30103,
      "@pgsql/utils": 8205,
      "@pyramation/postgraphile-plugin-fulltext-filter": 939,
      "graphile-column-privileges-mutations": 21,
      "libpg-query": 27899,
      "pg-proto-parser": 9,
      "pg-query-native-latest": 3,
      "pg-utils": 18,
      "pgsql-deparser": 26948,
      "pgsql-enums": 26949,
      "pgsql-parser": 18801
    }
  },
  "protobufs": {
    "total": 18160,
    "packages": {
      "@protobufs/cosmos": 1008,
      "@protobufs/google": 1313,
      "@protobufs/gogoproto": 1307,
      "@protobufs/cosmwasm": 218,
      "@protobufs/tendermint": 998,
      "@protobufs/ibc": 257,
      "@protobufs/cosmos_proto": 999,
      "@protobufs/osmosis": 82,
      "@protobufs/secret": 16,
      "@protobufs/juno": 15,
      "@protobufs/akash": 15,
      "@protobufs/regen": 16,
      "@protobufs/pylons": 13,
      "@protobufs/stargaze": 17,
      "@protobufs/bcna": 12,
      "@protobufs/comdex": 11,
      "@protobufs/evmos": 10,
      "@protobufs/axelar": 10,
      "@protobufs/amino": 259,
      "@cosmology/protobufjs": 10690,
      "@pyramation/protobufjs": 894
    }
  },
  "utils": {
    "total": null,
    "packages": {
      "ast-stringify": 8608,
      "nested-obj": 8487,
      "schema-typescript": 168,
      "etag-hash": 340,
      "uuid-hash": 206,
      "inquirerer": 8853,
      "publish-scripts": 81,
      "skitch-template": 5
    }
  }
}